README
flask_canvas.py
setup.py
flask_canvas.egg-info/PKG-INFO
flask_canvas.egg-info/SOURCES.txt
flask_canvas.egg-info/dependency_links.txt
flask_canvas.egg-info/requires.txt
flask_canvas.egg-info/top_level.txt