Metadata-Version: 1.1
Name: flask-canvas
Version: 0.1
Summary: A Flask extension for Facebook canvas-based apps
Home-page: https://github.com/demianbrecht/flask-canvas
Author: Demian Brecht
Author-email: demianbrecht@gmail.com
License: MIT
Keywords: python,facebook,canvas,oauth2
Platform: any
Classifier: Environment :: Web Environment
Classifier: License :: OSI Approved :: MIT License
Classifier: Intended Audience :: Developers
Classifier: Operating System :: OS Independent
Classifier: Programming Language :: Python
Classifier: Topic :: Software Development :: Libraries :: Python Modules
Classifier: Development Status :: 4 - Beta
